ulog/__init__.py
ulog/_ulog.py
ulog-0.3.3.dist-info/DESCRIPTION.rst
ulog-0.3.3.dist-info/METADATA
ulog-0.3.3.dist-info/RECORD
ulog-0.3.3.dist-info/WHEEL
ulog-0.3.3.dist-info/metadata.json
ulog-0.3.3.dist-info/top_level.txt
