Metadata-Version: 2.0
Name: ulog
Version: 0.3.3
Summary: Simple decorator based logger
Home-page: https://github.com/MrUPGrade/ulog
Author: Jakub (Mr. UPGrade) Czapliński
Author-email: sirupgrade@gmail.com
License: MIT
Platform: UNKNOWN
Classifier: Development Status :: 3 - Alpha
Classifier: Programming Language :: Python :: 2.6
Classifier: Programming Language :: Python :: 2.7
Classifier: Programming Language :: Python :: 3.3
Classifier: Programming Language :: Python :: 3.4
Classifier: Programming Language :: Python :: 3.5
Classifier: Programming Language :: Python :: 3.6
Requires-Dist: six (>=1.10.0)
Requires-Dist: enum34
Requires-Dist: funcsigs (>=0.4)
Requires-Dist: future
Requires-Dist: wrapt (>=1.10.6)
Provides-Extra: dev
Requires-Dist: ipython; extra == 'dev'
Requires-Dist: wheel; extra == 'dev'
Provides-Extra: test
Requires-Dist: coverage (>=4.0.0); extra == 'test'
Requires-Dist: mock (>=1.3); extra == 'test'
Requires-Dist: pytest; extra == 'test'
Requires-Dist: pytest-cov; extra == 'test'
